pyfsnotif/__init__.py
pyfsnotif/command.py
pyfsnotif/inotify.py
pyfsnotif/watcher.py
pyfsnotif-1.3.0.dist-info/LICENSE
pyfsnotif-1.3.0.dist-info/METADATA
pyfsnotif-1.3.0.dist-info/WHEEL
pyfsnotif-1.3.0.dist-info/entry_points.txt
pyfsnotif-1.3.0.dist-info/top_level.txt
pyfsnotif-1.3.0.dist-info/RECORD
