Metadata-Version: 2.1
Name: pyfsnotif
Version: 1.3.0
Summary: inotifier
Home-page: https://gitlab.com/dugres/pyfsnotif/tree/stable
Author: Louis RIVIERE
Author-email: louis@riviere.xyz
License: MIT
Keywords: utility
Platform: UNKNOWN
Classifier: Development Status :: 4 - Beta
Classifier: Intended Audience :: Developers
Classifier: Topic :: Software Development :: Testing
Classifier: License :: OSI Approved :: MIT License
Classifier: Programming Language :: Python :: 3
License-File: LICENSE
